sqlalchemy_cloudsqlite/__init__.py
sqlalchemy_cloudsqlite/dialect.py
sqlalchemy_cloudsqlite/storage.py
sqlalchemy_cloudsqlite-0.1.0.dev0.dist-info/LICENSE
sqlalchemy_cloudsqlite-0.1.0.dev0.dist-info/METADATA
sqlalchemy_cloudsqlite-0.1.0.dev0.dist-info/WHEEL
sqlalchemy_cloudsqlite-0.1.0.dev0.dist-info/entry_points.txt
sqlalchemy_cloudsqlite-0.1.0.dev0.dist-info/top_level.txt
sqlalchemy_cloudsqlite-0.1.0.dev0.dist-info/RECORD
