Metadata-Version: 2.1
Name: sqlalchemy-cloudsqlite
Version: 0.1.0.dev0
Summary: SQLite for Serverless Computing
Home-page: https://github.com/njannasch/SQLAlchemy-CloudSQLite
Author: Nils Jannasch
Author-email: nils@njann.de
License: MIT
Platform: UNKNOWN
Requires-Python: >=3.6
Requires-Dist: sqlalchemy
Requires-Dist: boto3
